spconv/__init__.py
spconv/conv.py
spconv/functional.py
spconv/identity.py
spconv/libspconv.so
spconv/modules.py
spconv/ops.py
spconv/pool.py
spconv/spconv_utils.cpython-310-x86_64-linux-gnu.so
spconv/spconv_utils.cpython-310-x86_64-linux-gnu.so.1
spconv/spconv_utils.cpython-310-x86_64-linux-gnu.so.1.1
spconv/tables.py
spconv/test_utils.py
spconv/utils/__init__.py
spconv_v1_2_1.libs/libabsl_bad_optional_access-702c25a7.so.2407.0.0
spconv_v1_2_1.libs/libabsl_bad_variant_access-cb1c175b.so.2407.0.0
spconv_v1_2_1.libs/libabsl_base-70cf9cd9.so.2407.0.0
spconv_v1_2_1.libs/libabsl_city-243ce93f.so.2407.0.0
spconv_v1_2_1.libs/libabsl_civil_time-6911b6d4.so.2407.0.0
spconv_v1_2_1.libs/libabsl_cord-14e20731.so.2407.0.0
spconv_v1_2_1.libs/libabsl_cord_internal-fd63a039.so.2407.0.0
spconv_v1_2_1.libs/libabsl_cordz_functions-fe2b0ca0.so.2407.0.0
spconv_v1_2_1.libs/libabsl_cordz_handle-eba5887c.so.2407.0.0
spconv_v1_2_1.libs/libabsl_cordz_info-4e0288c1.so.2407.0.0
spconv_v1_2_1.libs/libabsl_crc32c-0aeb4d49.so.2407.0.0
spconv_v1_2_1.libs/libabsl_crc_cord_state-c75814ed.so.2407.0.0
spconv_v1_2_1.libs/libabsl_crc_cpu_detect-f9c36670.so.2407.0.0
spconv_v1_2_1.libs/libabsl_crc_internal-e5640441.so.2407.0.0
spconv_v1_2_1.libs/libabsl_debugging_internal-542112c0.so.2407.0.0
spconv_v1_2_1.libs/libabsl_decode_rust_punycode-d84c2524.so.2407.0.0
spconv_v1_2_1.libs/libabsl_demangle_internal-5cc5f859.so.2407.0.0
spconv_v1_2_1.libs/libabsl_demangle_rust-91a9d23b.so.2407.0.0
spconv_v1_2_1.libs/libabsl_die_if_null-61cc0cf1.so.2407.0.0
spconv_v1_2_1.libs/libabsl_examine_stack-dd75f106.so.2407.0.0
spconv_v1_2_1.libs/libabsl_exponential_biased-a44f63a4.so.2407.0.0
spconv_v1_2_1.libs/libabsl_flags_commandlineflag-d03295b4.so.2407.0.0
spconv_v1_2_1.libs/libabsl_flags_commandlineflag_internal-79f9af0b.so.2407.0.0
spconv_v1_2_1.libs/libabsl_flags_config-2c999d2d.so.2407.0.0
spconv_v1_2_1.libs/libabsl_flags_internal-e09b4853.so.2407.0.0
spconv_v1_2_1-1.2.1.dist-info/METADATA
spconv_v1_2_1-1.2.1.dist-info/WHEEL
spconv_v1_2_1-1.2.1.dist-info/top_level.txt
spconv_v1_2_1-1.2.1.dist-info/RECORD
spconv_v1_2_1-1.2.1.dist-info/licenses/LICENSE
